Metadata-Version: 2.4
Name: aloo
Version: 1
Summary: Simple Test Script
Author: Anonymous Hackers
Author-email: admin@anonymous.com
Classifier: Programming Language :: Python :: 3
Classifier: Operating System :: OS Independent
Requires-Python: >=3.6
License-File: LICENCE.txt
Dynamic: author
Dynamic: author-email
Dynamic: classifier
Dynamic: description
Dynamic: description-content-type
Dynamic: license-file
Dynamic: requires-python
Dynamic: summary
